{"products":[{"id":"b22d7976-c6f1-4ad2-ab08-cdc85b5a9e1e","name":"Television","price":20000000,"category":"Electronics","stock":50},{"id":"c06e3123-aac0-465c-abae-a1365b470006","name":"Television","price":20000000,"category":"Electronics","stock":50},{"id":"1a49432c-aa86-4ebc-9577-3dbb113636f9","name":"Television","price":20000000,"category":"Electronics","stock":"50"},{"id":"df83929f-bb70-4d61-96cf-4699e384fb3e","name":"Television","price":20000000,"category":"Electronics","stock":"50"},{"id":"a7367241-0678-4a7f-9258-8a199b58c7e5","name":"Television","price":"20000000","category":"Electronics","stock":"50"},{"id":"ac9cb99f-2790-4716-af9b-f41b29c2755f","name":"Television","price":"20000000","category":"Electronics","stock":500},{"id":"79b4ea94-c4e6-47e4-aef5-118d904897f2","name":"Microwave","price":10000000,"category":"Electronics","stock":100},{"id":"6841d5d0-63ec-4505-956e-9130f9a0b326","name":"Microwave","price":10000000,"category":"Electronics","stock":100},{"id":"bad549e8-2ff9-40a5-844c-8a4c86dc034d","name":"Television","price":20000000,"category":"Electronics","stock":500},{"id":"fa30d607-d6f9-4de4-b2c2-4fa3999dfcb5","name":"Television","price":20000000,"category":"Electronics","stock":50}]}